SplinePoliMi/BasisFunction.h
SplinePoliMi/CLibrary.py
SplinePoliMi/ComputeSpline.h
SplinePoliMi/Main.cpp
SplinePoliMi/Settings.h
SplinePoliMi/Spline.h
SplinePoliMi/Spline.py
SplinePoliMi/Utilities.h
SplinePoliMi/__init__.py
SplinePoliMi-0.0.0.10.dist-info/METADATA
SplinePoliMi-0.0.0.10.dist-info/WHEEL
SplinePoliMi-0.0.0.10.dist-info/top_level.txt
SplinePoliMi-0.0.0.10.dist-info/RECORD
